realtime/__init__.py
realtime/buildin.py
realtime/monitor.py
RTvisualize-1.1.19.dist-info/LICENSE
RTvisualize-1.1.19.dist-info/METADATA
RTvisualize-1.1.19.dist-info/WHEEL
RTvisualize-1.1.19.dist-info/top_level.txt
RTvisualize-1.1.19.dist-info/RECORD
