Metadata-Version: 2.1
Name: RTvisualize
Version: 1.1.19
Summary: A general purpose realtime visualization
Home-page: https://github.com/janursa/RTvisualize
Author: Jalil Nourisa
Author-email: jalil.nourisa@gmail.com
License: UNKNOWN
Platform: UNKNOWN
Classifier: Programming Language :: Python :: 3
Classifier: License :: OSI Approved :: MIT License
Classifier: Operating System :: OS Independent
Requires-Python: >=3.7
Requires-Dist: dash (>=1.12)
Requires-Dist: plotly (>=4.6.0)
Requires-Dist: pandas (>=1.0.3)
Requires-Dist: numpy (>=1.18.4)
